[
  {
    "Key": "reminder_add",
    "Phrase": "When do you want to depart? Just type a time like '18:00', '6:00pm' or 'in 15 minutes'."
  },
  {
    "Key": "tutorial_auth",
    "Phrase": "I will be making channels for you and your hungry friends, so I need your authorization. Please authorize me:"
  },
  {
    "Key": "reminder_archive",
    "Phrase": "Alright then.. you can archive the channel <#%s> now."
  },
  {
    "Key": "reminder_add_invalid_input",
    "Phrase": "I need the time. Try something like '18:00', '6:00pm' or in '15 minutes'."
  },
  {
    "Key": "error_2",
    "Phrase": "shhh... I'm taking a poll now :)"
  },
  {
    "Key": "location_2",
    "Phrase": "Select your location by typing the number."
  },
  {
    "Key": "poll_tied",
    "Phrase": "%s restaurants tied. I chose %s for you."
  },
  {
    "Key": "reminder_1",
    "Phrase": "Restaurant decided! \n\n%s\n\nDo you want to set a reminder so nobody misses out?"
  },
  {
    "Key": "error_4",
    "Phrase": "OK! Just tell me whenever you don't know what to eat."
  },
  {
    "Key": "reminder_stop",
    "Phrase": "Ok! I'm not setting a reminder."
  },
  {
    "Key": "main_auth",
    "Phrase": "Remember, I need to make channels for you and your hungry friends, so I need your authorization. Please authorize me:"
  },
  {
    "Key": "main_auth_success",
    "Phrase": "Thanks! Let's find a good restaurant!"
  },
  {
    "Key": "reminder_added",
    "Phrase": "All set. I'll send direct messages to everyone at <%s>."
  },
  {
    "Key": "tutorial_2",
    "Phrase": "Thanks! Let's see how it works!"
  },
  {
    "Key": "error_1",
    "Phrase": "Sorry, I don't understand. Send me `What to eat`, then I will help you find restaurants.\n\nOr send `demo` to go through know how it works."
  },
  {
    "Key": "poll_joke",
    "Phrase": "Uh oh.. looks like someone is going to have a lonely dinner....."
  },
  {
    "Key": "error_8",
    "Phrase": "No restaurant found. try using other search keywords."
  },
  {
    "Key": "location_4",
    "Phrase": "Here's some tasty options for %s"
  },
  {
    "Key": "poll_result",
    "Phrase": "Great! %s is the winner."
  },
  {
    "Key": "channel_create",
    "Phrase": "bopbot_%s"
  },
  {
    "Key": "tutorial_5",
    "Phrase": "At this point, I'll ask you who you're going to eat with and send them the restaurant poll. Then I'll make a new channel and invite everyone.\n\nI'd do it now but..this is just a demo and I don't want to bother anyone right now. I'll be ready whenever you're hungry though!\n\nJust type `What to eat?` when you want a restaurant recommendation :)"
  },
  {
    "Key": "reminder_text",
    "Phrase": "Departure time!!\nLet's go to %s!"
  },
  {
    "Key": "tutorial_4",
    "Phrase": "You're not going to eat alone, right? How about asking your friends which restaurants they prefer?\n\nClick the 'send the poll' button."
  },
  {
    "Key": "tutorial_1",
    "Phrase": "Hi, I'm whattoeat bot. I will help you find good restaurants.\nSend me `What to eat?` in a direct message, and I'll get started. Oh, and you should really share me with your friends and co-workers ;)\n\nLet's start with a simple demo?"
  },
  {
    "Key": "tutorial_3",
    "Phrase": "These restaurants are yummy, but if you don't like them you can see more options.\n\nClick the 'more options' button."
  },
  {
    "Key": "error_5",
    "Phrase": "I'm sorry. I can't stop now, since you already made a channel. If you don't want to take a poll, archive the channel."
  },
  {
    "Key": "error_9",
    "Phrase": "Um..what? :(\nSend `stop` to end the current conversation."
  },
  {
    "Key": "invite_invalid_input",
    "Phrase": "That was weird..try typing the username like `@username`. If you're scared and want to start over, just send `stop`."
  },
  {
    "Key": "reminder_result",
    "Phrase": "The organizer set a reminder for %s."
  },
  {
    "Key": "location_1",
    "Phrase": "Type your location"},
  {
    "Key": "error_6",
    "Phrase": "We're going through the demo now. If you want to start over, just send `stop`."
  },
  {
    "Key": "invite",
    "Phrase": "Who do you want to send the poll to? Type your the person's username like `@username`."
  },
  {
    "Key": "location_3",
    "Phrase": "or type your location to search again."
  },
  {
    "Key": "poll_channel_generated",
    "Phrase": "Channel generated.. Go to <#%s>."
  },
  {
    "Key": "poll_vote",
    "Phrase": "What should we eat? Vote by clicking your restaurant choice."
  },
  {
    "Key": "error_7",
    "Phrase": "Sorry, I don't understand :( If you don't want to go through the demo, just send `stop`."
  },
  {
    "Key": "error_3",
    "Phrase": "I'm trying to find you some nice restaurants now. if you want to start over, just send `stop`."
  }
]
